tableau_parser/__init__.py
tableau_parser/parser.py
tableau_parser-0.1.0.dist-info/licenses/LICENSE
tableau_parser-0.1.0.dist-info/METADATA
tableau_parser-0.1.0.dist-info/WHEEL
tableau_parser-0.1.0.dist-info/top_level.txt
tableau_parser-0.1.0.dist-info/RECORD
